deltalake/__init__.py
deltalake/_internal.abi3.so
deltalake/_internal.pyi
deltalake/_util.py
deltalake/exceptions.py
deltalake/fs/__init__.py
deltalake/fs/_base_handler.py
deltalake/fs/fs_handler.py
deltalake/py.typed
deltalake/query.py
deltalake/schema.py
deltalake/table.py
deltalake/transaction.py
deltalake/warnings.py
deltalake/writer/__init__.py
deltalake/writer/_conversion.py
deltalake/writer/_utils.py
deltalake/writer/convert_to.py
deltalake/writer/properties.py
deltalake/writer/writer.py
deltalake-1.3.2.dist-info/METADATA
deltalake-1.3.2.dist-info/WHEEL
deltalake-1.3.2.dist-info/licenses/LICENSE.txt
deltalake-1.3.2.dist-info/RECORD
