Metadata-Version: 2.4
Name: deltalake
Version: 1.3.2
Classifier: License :: OSI Approved :: Apache Software License
Classifier: Programming Language :: Python :: 3.10
Classifier: Programming Language :: Python :: 3.11
Classifier: Programming Language :: Python :: 3.12
Classifier: Programming Language :: Python :: 3.13
Classifier: Programming Language :: Python :: 3.14
Requires-Dist: arro3-core>=0.5.0
Requires-Dist: deprecated>=1.2.18
Requires-Dist: pandas ; extra == 'pandas'
Requires-Dist: pyarrow>=16 ; extra == 'pyarrow'
Provides-Extra: pandas
Provides-Extra: pyarrow
License-File: LICENSE.txt
Summary: Native Delta Lake Python binding based on delta-rs with Pandas integration
Keywords: deltalake,delta,datalake,pandas,arrow
Home-Page: https://github.com/delta-io/delta-rs
License-Expression: Apache-2.0
Requires-Python: >=3.10
Project-URL: documentation, https://delta-io.github.io/delta-rs/
Project-URL: repository, https://github.com/delta-io/delta-rs/tree/main/python/
